rnadtu/__init__.py
rnadtu/module1.py
rnadtu/module2.R
rnadtu/module3.py
rnadtu/module4.py
rnadtu/module5.R
rnadtu-0.1.8.dist-info/licenses/LICENSE
rnadtu-0.1.8.dist-info/METADATA
rnadtu-0.1.8.dist-info/WHEEL
rnadtu-0.1.8.dist-info/top_level.txt
rnadtu-0.1.8.dist-info/RECORD
