Metadata-Version: 2.4
Name: rnadtu
Version: 0.1.8
Summary: Package for running the CIDR algorithm implemented in R, in python
Author-email: Anton <s235256@dtu.dk>, Sigurd <s235215@dtu.dk>, Alex <s235237@dtu.dk>, Aryan <s224208@dtu.dk>
License-Expression: GPL-2.0
License-File: LICENSE
Requires-Dist: numpy<3.0,>=2.0.2
Requires-Dist: pandas<3.0,>=2.2.3
Requires-Dist: anndata<1.0,>=0.11
Requires-Dist: scanpy<2.0,>=1.9.8
Requires-Dist: rpy2<4.0,>=3.6.0
Requires-Dist: pyarrow>=15.0.0
Dynamic: license-file
